vantage_sdk/__init__.py
vantage_sdk/client.py
vantage_sdk/models/__init__.py
vantage_sdk/models/common.py
vantage_sdk/models/gen_models/BusinessMetrics_businessMetricToken_Values.py
vantage_sdk/models/gen_models/Integrations_integrationToken_Costs.py
vantage_sdk/models/gen_models/__init__.py
vantage_sdk/py.typed
client_for_vantage-1.0.0.dist-info/WHEEL
client_for_vantage-1.0.0.dist-info/METADATA
client_for_vantage-1.0.0.dist-info/RECORD
