Metadata-Version: 2.3
Name: client-for-vantage
Version: 1.0.0
Summary: An SDK for interacting with the Vantage API, attempts to maintain parity with the API, provides type safety via codegen Pydantic classes and manages pagination
Keywords: vantage,api,sdk
Author: Orest Tokovenko
Author-email: Orest Tokovenko <oresttokovenko@block.xyz>
License: Apache-2.0
Classifier: Development Status :: 5 - Production/Stable
Classifier: Programming Language :: Python :: 3
Classifier: Programming Language :: Python :: 3.10
Classifier: Programming Language :: Python :: 3.11
Classifier: Programming Language :: Python :: 3.12
Classifier: Topic :: Software Development :: Libraries :: Python Modules
Requires-Dist: pydantic>=2.10.6
Requires-Dist: pydantic-settings>=2.7.1
Requires-Dist: pydantic-extra-types>=2.10.2
Requires-Dist: httpx>=0.28.1
Requires-Dist: pendulum>=3.0.0
Requires-Python: >=3.10, <3.13
Project-URL: Homepage, https://github.com/block/client-for-vantage
Project-URL: Issues, https://github.com/block/client-for-vantage/issues
Project-URL: Repository, https://github.com/block/client-for-vantage
